batpy/__init__.py
batpy/batpac_battery.py
batpy/batpac_tool.py
batpy/batpy_workbook.py
batpy/brightway.py
batpy/data/0.0.0/batpy_batpac_battery_design.toml
batpy/data/0.0.0/batpy_batpac_calculation_and_validation_results.toml
batpy/data/0.0.0/batpy_batpac_config.toml
batpy/data/0.0.0/batpy_batpac_summary_of_results.toml
batpy/data/0.0.0/batpy_batpac_user_input_cells.toml
batpy/data/0.0.0/batpy_batteries_config.toml
batpy/data/0.1.0/batpy_batpac2brightway.toml
batpy/data/0.1.0/batpy_batpac_battery_design.toml
batpy/data/0.1.0/batpy_batpac_calculation_and_validation_results.toml
batpy/data/0.1.0/batpy_batpac_config.toml
batpy/data/0.1.0/batpy_batpac_summary_of_results.toml
batpy/data/0.1.0/batpy_batpac_user_input_cells.toml
batpy/data/0.1.0/batpy_batteries_config.toml
batpy/data/0.3.0/batpy_batpac2brightway.toml
batpy/data/0.3.0/batpy_batpac_battery_design.toml
batpy/data/0.3.0/batpy_batpac_calculation_and_validation_results.toml
batpy/data/0.3.0/batpy_batpac_config.toml
batpy/data/0.3.0/batpy_batpac_summary_of_results.toml
batpy/data/0.3.0/batpy_batpac_user_input_cells.toml
batpy/data/0.3.0/batpy_batteries_config.toml
batpy/data/__init__.py
batpy/data/excel_workbooks/BatPaC-Brightway.xlsx
batpy/datasets.py
batpy/formula_engine.py
batpy/utility_functions.py
batpy-0.3.0.dist-info/LICENSE
batpy-0.3.0.dist-info/METADATA
batpy-0.3.0.dist-info/WHEEL
batpy-0.3.0.dist-info/RECORD
