Metadata-Version: 2.1
Name: batpy
Version: 0.3.0
Summary: A python package to read, write, and calculate batteries in the BatPaC tool.
Home-page: https://github.com/rginster/batpy
License: MIT
Author: Raphael Ginster
Author-email: r.ginster@tu-braunschweig.de
Requires-Python: >=3.10,<4.0
Classifier: License :: OSI Approved :: MIT License
Classifier: Programming Language :: Python :: 3
Classifier: Programming Language :: Python :: 3.10
Classifier: Programming Language :: Python :: 3.11
Requires-Dist: pathlib (>=1.0.1,<2.0.0)
Requires-Dist: prettytable (>=3.7.0,<4.0.0)
Requires-Dist: semantic-version (>=2.10.0,<3.0.0)
Requires-Dist: toml (>=0.10.2,<0.11.0)
Requires-Dist: tqdm (>=4.65.0,<5.0.0)
Requires-Dist: xlwings (>=0.30.4,<0.31.0)
Project-URL: Documentation, https://rginster.github.io/batpy/
Project-URL: Repository, https://github.com/rginster/batpy
